proxy6api/__init__.py
proxy6api/client.py
proxy6api/settings/__init__.py
proxy6api/settings/bases.py
proxy6api/settings/errors.py
proxy6api/settings/typing_methods.py
proxy6api-1.0.0.dist-info/LICENSE
proxy6api-1.0.0.dist-info/WHEEL
proxy6api-1.0.0.dist-info/METADATA
proxy6api-1.0.0.dist-info/RECORD
