Metadata-Version: 2.1
Name: proxy6api
Version: 1.0.0
Summary: This is unofficial software for using api with proxy 6.net
License: MIT
Author: Konstantin Raikhert
Author-email: raikhert13@gmail.com
Requires-Python: >=3.10,<4.0
Classifier: License :: OSI Approved :: MIT License
Classifier: Programming Language :: Python :: 3
Classifier: Programming Language :: Python :: 3.10
Requires-Dist: requests (>=2.28.2,<3.0.0)
